README.md
setup.py
zx_forecasting_framework/__init__.py
zx_forecasting_framework/analyse.py
zx_forecasting_framework/metrics.py
zx_forecasting_framework/model.py
zx_forecasting_framework/timeSeriesObject.py
zx_forecasting_framework/transform.py
zx_forecasting_framework.egg-info/PKG-INFO
zx_forecasting_framework.egg-info/SOURCES.txt
zx_forecasting_framework.egg-info/dependency_links.txt
zx_forecasting_framework.egg-info/not-zip-safe
zx_forecasting_framework.egg-info/top_level.txt