Metadata-Version: 2.1
Name: zx-forecasting-framework
Version: 0.0.1
Summary: Forecasting framework for ZX projects
Home-page: UNKNOWN
Author: Tamojit Maiti, Shashi Bhushan Singh
Author-email: shashi.bhushansingh@ab-inbev.com
License: UNKNOWN
Platform: UNKNOWN
